incuna_surveys-0.17.1.dist-info/DESCRIPTION.rst
incuna_surveys-0.17.1.dist-info/METADATA
incuna_surveys-0.17.1.dist-info/RECORD
incuna_surveys-0.17.1.dist-info/WHEEL
incuna_surveys-0.17.1.dist-info/metadata.json
incuna_surveys-0.17.1.dist-info/top_level.txt
surveys/__init__.py
surveys/admin_forms.py
surveys/apps.py
surveys/base_admin.py
surveys/form_field_generators.py
surveys/generators.py
surveys/models.py
surveys/serializer_field_generators.py
surveys/serializers.py
surveys/urls.py
surveys/views_api.py
surveys/migrations/0001_initial.py
surveys/migrations/0002_change_percentage_display_text.py
surveys/migrations/0003_surveyfield_required.py
surveys/migrations/0004_surveyfieldset_description.py
surveys/migrations/0005_add_survey_model.py
surveys/migrations/0006_userresponse_date.py
surveys/migrations/0007_userresponse_precise_date_created.py
surveys/migrations/0008_answers_blank.py
surveys/migrations/0009_add_start_end_date.py
surveys/migrations/0010_orderable-ordering.py
surveys/migrations/0011_create_translation_models.py
surveys/migrations/0012_move_translation_data.py
surveys/migrations/0013_remove_old_fields.py
surveys/migrations/0014_to_survey_field_add_important_flag.py
surveys/migrations/__init__.py
surveys/tests/__init__.py
surveys/tests/factories.py
surveys/tests/test_admin_forms.py
surveys/tests/test_form_field_generators.py
surveys/tests/test_models.py
surveys/tests/test_serializer_field_generators.py
surveys/tests/test_serializers.py
surveys/tests/test_translations.py
surveys/tests/test_urls.py
surveys/tests/test_views_api.py
surveys/tests/urls.py
surveys/tests/utils.py
