Metadata-Version: 2.0
Name: incuna-surveys
Version: 0.17.1
Summary: Allows the creation of custom questionnaires and surveys via the Django admin.
Home-page: https://github.com/incuna/incuna-surveys
Author: Incuna Ltd
Author-email: admin@incuna.com
License: UNKNOWN
Platform: UNKNOWN
Classifier: Environment :: Web Environment
Classifier: Framework :: Django
Classifier: Intended Audience :: Developers
Classifier: License :: OSI Approved :: BSD License
Classifier: Programming Language :: Python :: 3
Classifier: Programming Language :: Python :: 3.4
Classifier: Programming Language :: Python :: 3.5
Classifier: Topic :: Software Development
Classifier: Topic :: Utilities
Requires-Dist: django-orderable (>=4.0.5,<4.1)
Requires-Dist: django-parler (<1.8,>=1.7.0)
